kodi_cli/driver.py
kodi_cli/json-defs/methods.json
kodi_cli/json-defs/types.json
kodi_cli/json-defs/version.txt
kodi_cli/kodi_help_tester.py
kodi_cli/kodi_interface.py
kodi_cli/kodi_libraray_inventory.py
kodi_cli/utils/cfg.py
kodi_cli/utils/kodi_common.py
kodi_cli/utils/kodi_output_factory.py
kodi_cli-0.2.6.dist-info/entry_points.txt
kodi_cli-0.2.6.dist-info/LICENSE
kodi_cli-0.2.6.dist-info/METADATA
kodi_cli-0.2.6.dist-info/WHEEL
kodi_cli-0.2.6.dist-info/RECORD
