Metadata-Version: 2.3
Name: kodi-cli
Version: 0.2.6
Summary: Control your Kodi instance(s) via the commandline
License: MIT
Author: Al D'Amico
Author-email: JavaWiz1@hotmail.com
Requires-Python: >=3.8
Classifier: License :: OSI Approved :: MIT License
Classifier: Programming Language :: Python :: 3
Classifier: Programming Language :: Python :: 3.8
Classifier: Programming Language :: Python :: 3.9
Classifier: Programming Language :: Python :: 3.10
Classifier: Programming Language :: Python :: 3.11
Classifier: Programming Language :: Python :: 3.12
Classifier: Programming Language :: Python :: 3.13
Requires-Dist: loguru
Requires-Dist: requests (>=2.32.3,<3.0.0)
